rjango/__init__.py
rjango/core/__init__.py
rjango/core/apps.py
rjango/core/commands/__init__.py
rjango/core/commands/inspectdb.py
rjango/core/commands/sqlmigrate.py
rjango/core/decorators.py
rjango/core/schema.py
rjango/core/settings.py
rjango/core/setup.py
rjango/main.py
rjango/migrations_template/__init__.py
rjango/migrations_template/empty/__init__.py
rjango/migrations_template/empty/migrations/__init__.py
rjango/migrations_template/empty/models/__init__.py
rjango/migrations_template/example/__init__.py
rjango/migrations_template/example/migrations/__init__.py
rjango/migrations_template/example/models/__init__.py
rjango/migrations_template/example/models/author.py
rjango/migrations_template/example/models/book.py
rjango/migrations_template/example/models/reader.py
rjango/migrations_template/example/models/relations.py
rjango/utils/__init__.py
rjango/utils/common.py
rjango-0.5.0.dist-info/LICENSE
rjango-0.5.0.dist-info/METADATA
rjango-0.5.0.dist-info/WHEEL
rjango-0.5.0.dist-info/entry_points.txt
rjango-0.5.0.dist-info/RECORD
