Metadata-Version: 2.3
Name: rjango
Version: 0.5.0
Summary: rjango is a tool that automatically generates up and down migration files for rust sqlx
Author: hushoujier@qq.com
Requires-Python: >=3.10,<4
Classifier: Programming Language :: Python :: 3
Classifier: Programming Language :: Python :: 3.10
Classifier: Programming Language :: Python :: 3.11
Classifier: Programming Language :: Python :: 3.12
Classifier: Programming Language :: Python :: 3.13
Requires-Dist: django (>=5.1.5,<6.0.0)
Requires-Dist: django-environ (>=0.12.0,<0.13.0)
Requires-Dist: typer (>=0.15.1,<0.16.0)
